{
  "fitnes": [
    {
      "img": "img/tab/tag_photo_1.png",
      "title": "Пульсометр Polar FT1",
      "descr": "Для первых шагов в тренировках, основанных на сердечном ритме",
      "old": "4 750 руб.",
      "now": "4 750 руб.",
      "wishes": [
        "Вы услышите звуковое оповещение о нужном пульсе во время тренировки;",
        "Вы увидите информативный графический индикатор целевых тренировочных зон пульса;",
        "Также Вы увидите информацию о расходе калорий за тренировку;",
        "Вы сможете посмотреть данные по 10 тренировкам"
      ],
      "name": true
    }
  ],
  "run": [
    {
      "img": "img/tab/tag_photo_1.png",
      "title": "Пульсометр Polar FT1",
      "descr": "Для первых шагов в тренировках, основанных на сердечном ритме",
      "old": "4 750 руб.",
      "now": "4 750 руб.",
      "wishes": [
        "Вы услышите звуковое оповещение о нужном пульсе во время тренировки;",
        "Вы увидите информативный графический индикатор целевых тренировочных зон пульса;"
      ],
      "name": false
    }
  ],
  "requests": [
    {
      "name": "Виктор",
      "phone": "89473847594",
      "id": 1
    },
    {
      "name": "Олег",
      "phone": "896666666666",
      "id": 2
    },
    {
      "name": "Глеб",
      "phone": "89765785986",
      "id": 3
    },
    {
      "name": "Цацурина",
      "phone": "89763563837373",
      "id": 4
    }
  ]
}